sol/__init__.py
sol/base58.py
sol/config.py
sol/core.py
sol/denomination.py
sol/ed25519.py
sol/eddsa.py
sol/rpc.py
sol/wallet.py
solya-0.2.0.dist-info/METADATA
solya-0.2.0.dist-info/WHEEL
solya-0.2.0.dist-info/licenses/LICENSE
solya-0.2.0.dist-info/RECORD
